{
  "Official Documents of NGO ": [
            {
              "title": "Letter from HH The Dalai Lama's Office",
              "image": "/assets/about-images/HH_letter.jpeg"
            },
            {
              "title": "Letter from Shisur Lobsang Sangye Office",  
              "image": "/assets/about-images/Shisur Lobsang Sangye Office1.png"
            },
            {
              "title": "Letter from Tibetan Parliament",
              "image": "/assets/about-images/Tibetan Parliament Letter2.png"
            },
              {
              "title": "UICC Registration Certificate",
              "image": "/assets/about-images/UICC Registration Member3.png"
            },
            {
              "title": "Letter from Shri Kiran Rijiju's Office",
              "image": "/assets/about-images/Kiran Rijiju Office4.png"
            },
            {
              "title": "Letter from Parlad Singh Sawhney",
              "image": "/assets/about-images/parlad singh sawhney letter5.png"
            },
            {
              "title": "Letter from Kriti Jepa Monastery",
              "image": "/assets/about-images/kriti jepa monastery6.png"
            },
            {
              "title": "Letter from Department of Health, CTA",
              "image": "/assets/about-images/department of health cta7.png"
            },
            {
              "title": "Letter from Bureau Office, Delhi",
              "image": "/assets/about-images/bureau office Delhi8.png"
            },
            {
              "title": "Letter from RTYC, Delhi",
              "image": "/assets/about-images/rtyc delhi appreciation9.png"
            },
            {
              "title": "12a Certificate",
              "image": "/assets/about-images/12a10.png"
            },
            {
              "title": "80g Certificate",
              "image": "/assets/about-images/80g11.png"
            },
            {
              "title": "CSR Certificate",
              "image": "/assets/about-images/CSR Certificate12.png"
            },
            {
              "title": "NGO Darpan",
              "image": "/assets/about-images/NGO Darpan13.png"
            }
          ]
        }